ChanpinshejiTihuiSujie20161/README.md
ChanpinshejiTihuiSujie20161/__init__.py
ChanpinshejiTihuiSujie20161/__main__.py
ChanpinshejiTihuiSujie20161/file.epub
ChanpinshejiTihuiSujie20161/index.html
ChanpinshejiTihuiSujie20161/css/__init__.py
ChanpinshejiTihuiSujie20161/css/annotations.css
ChanpinshejiTihuiSujie20161/css/main.css
ChanpinshejiTihuiSujie20161/css/normalize.css
ChanpinshejiTihuiSujie20161/css/popup.css
ChanpinshejiTihuiSujie20161/font/__init__.py
ChanpinshejiTihuiSujie20161/font/fontello.eot
ChanpinshejiTihuiSujie20161/font/fontello.svg
ChanpinshejiTihuiSujie20161/font/fontello.ttf
ChanpinshejiTihuiSujie20161/font/fontello.woff
ChanpinshejiTihuiSujie20161/img/__init__.py
ChanpinshejiTihuiSujie20161/img/annotator-glyph-sprite.png
ChanpinshejiTihuiSujie20161/img/annotator-icon-sprite.png
ChanpinshejiTihuiSujie20161/img/apple-touch-icon.png
ChanpinshejiTihuiSujie20161/img/cancelfullscreen.png
ChanpinshejiTihuiSujie20161/img/close.png
ChanpinshejiTihuiSujie20161/img/fullscreen.png
ChanpinshejiTihuiSujie20161/img/loader.gif
ChanpinshejiTihuiSujie20161/img/menu-icon.png
ChanpinshejiTihuiSujie20161/img/save.png
ChanpinshejiTihuiSujie20161/img/saved.png
ChanpinshejiTihuiSujie20161/img/settings-s.png
ChanpinshejiTihuiSujie20161/img/settings.png
ChanpinshejiTihuiSujie20161/img/star.png
ChanpinshejiTihuiSujie20161/js/__init__.py
ChanpinshejiTihuiSujie20161/js/epub.js
ChanpinshejiTihuiSujie20161/js/epub.min.js
ChanpinshejiTihuiSujie20161/js/epub.min.map
ChanpinshejiTihuiSujie20161/js/hooks.min.js
ChanpinshejiTihuiSujie20161/js/hooks.min.map
ChanpinshejiTihuiSujie20161/js/reader.js
ChanpinshejiTihuiSujie20161/js/reader.js.map
ChanpinshejiTihuiSujie20161/js/reader.min.js
ChanpinshejiTihuiSujie20161/js/reader.min.map
ChanpinshejiTihuiSujie20161/js/hooks/__init__.py
ChanpinshejiTihuiSujie20161/js/hooks/extensions/__init__.py
ChanpinshejiTihuiSujie20161/js/hooks/extensions/highlight.js
ChanpinshejiTihuiSujie20161/js/libs/__init__.py
chanpinsheji_tihui_sujie_2016_1-2024.3.1.0.dist-info/METADATA
chanpinsheji_tihui_sujie_2016_1-2024.3.1.0.dist-info/WHEEL
chanpinsheji_tihui_sujie_2016_1-2024.3.1.0.dist-info/entry_points.txt
chanpinsheji_tihui_sujie_2016_1-2024.3.1.0.dist-info/top_level.txt
chanpinsheji_tihui_sujie_2016_1-2024.3.1.0.dist-info/RECORD
